README.md
setup.cfg
setup.py
datalab_utils/__about__.py
datalab_utils/__init__.py
datalab_utils/bigquery.py
datalab_utils/storage.py
datalab_utils.egg-info/PKG-INFO
datalab_utils.egg-info/SOURCES.txt
datalab_utils.egg-info/dependency_links.txt
datalab_utils.egg-info/requires.txt
datalab_utils.egg-info/top_level.txt